setup.py
bisect_b2g/__init__.py
bisect_b2g/bisection.py
bisect_b2g/driver.py
bisect_b2g/evaluator.py
bisect_b2g/history.py
bisect_b2g/repository.py
bisect_b2g/util.py
bisect_b2g.egg-info/PKG-INFO
bisect_b2g.egg-info/SOURCES.txt
bisect_b2g.egg-info/dependency_links.txt
bisect_b2g.egg-info/entry_points.txt
bisect_b2g.egg-info/requires.txt
bisect_b2g.egg-info/top_level.txt