Metadata-Version: 1.0
Name: bisect-b2g
Version: 1
Summary: This program is used to bisect multiple repositories
Home-page: http://github.com/mozilla-b2g/b2g_bisect
Author: John Ford
Author-email: john@johnford.info
License: MPL2
Keywords: b2g gaia bisect
Platform: UNKNOWN
